[
  {"municipio": "ACAUÃ", "eleitorado": 6289},
  {"municipio": "AGRICOLÂNDIA", "eleitorado": 5596},
  {"municipio": "ÁGUA BRANCA", "eleitorado": 15874},
  {"municipio": "ALAGOINHA DO PIAUÍ", "eleitorado": 6232},
  {"municipio": "ALEGRETE DO PIAUÍ", "eleitorado": 4613},
  {"municipio": "ALTO LONGÁ", "eleitorado": 12803},
  {"municipio": "ALTOS", "eleitorado": 35736},
  {"municipio": "ALVORADA DO GURGUÉIA", "eleitorado": 4774},
  {"municipio": "AMARANTE", "eleitorado": 16165},
  {"municipio": "ANGICAL DO PIAUÍ", "eleitorado": 6752},
  {"municipio": "ANÍSIO DE ABREU", "eleitorado": 6921},
  {"municipio": "ANTÔNIO ALMEIDA", "eleitorado": 3143},
  {"municipio": "AROAZES", "eleitorado": 5677},
  {"municipio": "AROEIRAS DO ITAIM", "eleitorado": 4377},
  {"municipio": "ARRAIAL", "eleitorado": 4350},
  {"municipio": "ASSUNÇÃO DO PIAUÍ", "eleitorado": 7836},
  {"municipio": "AVELINO LOPES", "eleitorado": 9654},
  {"municipio": "BAIXA GRANDE DO RIBEIRO", "eleitorado": 11354},
  {"municipio": "BARRA D'ALCÂNTARA", "eleitorado": 3623},
  {"municipio": "BARRAS", "eleitorado": 38388},
  {"municipio": "BARREIRAS DO PIAUÍ", "eleitorado": 3840},
  {"municipio": "BARRO DURO", "eleitorado": 6432},
  {"municipio": "BATALHA", "eleitorado": 22833},
  {"municipio": "BELA VISTA DO PIAUÍ", "eleitorado": 3406},
  {"municipio": "BELÉM DO PIAUÍ", "eleitorado": 3075},
  {"municipio": "BENEDITINOS", "eleitorado": 9611},
  {"municipio": "BERTOLÍNIA", "eleitorado": 5057},
  {"municipio": "BETÂNIA DO PIAUÍ", "eleitorado": 5645},
  {"municipio": "BOA HORA", "eleitorado": 6928},
  {"municipio": "BOCAINA", "eleitorado": 5803},
  {"municipio": "BOM JESUS", "eleitorado": 19467},
  {"municipio": "BOM PRINCÍPIO DO PIAUÍ", "eleitorado": 6796},
  {"municipio": "BONFIM DO PIAUÍ", "eleitorado": 5049},
  {"municipio": "BOQUEIRÃO DO PIAUÍ", "eleitorado": 5974},
  {"municipio": "BRASILEIRA", "eleitorado": 8898},
  {"municipio": "BREJO DO PIAUÍ", "eleitorado": 3835},
  {"municipio": "BURITI DOS LOPES", "eleitorado": 17461},
  {"municipio": "BURITI DOS MONTES", "eleitorado": 6928},
  {"municipio": "CABECEIRAS DO PIAUÍ", "eleitorado": 9957},
  {"municipio": "CAJAZEIRAS DO PIAUÍ", "eleitorado": 3806},
  {"municipio": "CAJUEIRO DA PRAIA", "eleitorado": 7487},
  {"municipio": "CALDEIRÃO GRANDE DO PIAUÍ", "eleitorado": 5179},
  {"municipio": "CAMPINAS DO PIAUÍ", "eleitorado": 5554},
  {"municipio": "CAMPO ALEGRE DO FIDALGO", "eleitorado": 4528},
  {"municipio": "CAMPO GRANDE DO PIAUÍ", "eleitorado": 5295},
  {"municipio": "CAMPO LARGO DO PIAUÍ", "eleitorado": 5902},
  {"municipio": "CAMPO MAIOR", "eleitorado": 35760},
  {"municipio": "CANAVIEIRA", "eleitorado": 3595},
  {"municipio": "CANTO DO BURITI", "eleitorado": 16350},
  {"municipio": "CAPITÃO DE CAMPOS", "eleitorado": 10578},
  {"municipio": "CAPITÃO GERVÁSIO OLIVEIRA", "eleitorado": 4009},
  {"municipio": "CARACOL", "eleitorado": 8486},
  {"municipio": "CARAÚBAS DO PIAUÍ", "eleitorado": 5242},
  {"municipio": "CARIDADE DO PIAUÍ", "eleitorado": 4985},
  {"municipio": "CASTELO DO PIAUÍ", "eleitorado": 16984},
  {"municipio": "CAXINGÓ", "eleitorado": 5727},
  {"municipio": "COCAL", "eleitorado": 22640},
  {"municipio": "COCAL DE TELHA", "eleitorado": 4709},
  {"municipio": "COCAL DOS ALVES", "eleitorado": 5659},
  {"municipio": "COIVARAS", "eleitorado": 5652},
  {"municipio": "COLÔNIA DO GURGUÉIA", "eleitorado": 5616},
  {"municipio": "COLÔNIA DO PIAUÍ", "eleitorado": 6343},
  {"municipio": "CONCEIÇÃO DO CANINDÉ", "eleitorado": 4940},
  {"municipio": "CORONEL JOSÉ DIAS", "eleitorado": 5427},
  {"municipio": "CORRENTE", "eleitorado": 21481},
  {"municipio": "CRISTALÂNDIA DO PIAUÍ", "eleitorado": 6229},
  {"municipio": "CRISTINO CASTRO", "eleitorado": 8455},
  {"municipio": "CURIMATÁ", "eleitorado": 9392},
  {"municipio": "CURRAIS", "eleitorado": 6221},
  {"municipio": "CURRALINHOS", "eleitorado": 5292},
  {"municipio": "CURRAL NOVO DO PIAUÍ", "eleitorado": 5249},
  {"municipio": "DEMERVAL LOBÃO", "eleitorado": 13412},
  {"municipio": "DIRCEU ARCOVERDE", "eleitorado": 6704},
  {"municipio": "DOM EXPEDITO LOPES", "eleitorado": 6422},
  {"municipio": "DOMINGOS MOURÃO", "eleitorado": 4384},
  {"municipio": "DOM INOCÊNCIO", "eleitorado": 7508},
  {"municipio": "ELESBÃO VELOSO", "eleitorado": 13759},
  {"municipio": "ELISEU MARTINS", "eleitorado": 4047},
  {"municipio": "ESPERANTINA", "eleitorado": 32384},
  {"municipio": "FARTURA DO PIAUÍ", "eleitorado": 4797},
  {"municipio": "FLORES DO PIAUÍ", "eleitorado": 4368},
  {"municipio": "FLORESTA DO PIAUÍ", "eleitorado": 2644},
  {"municipio": "FLORIANO", "eleitorado": 44560},
  {"municipio": "FRANCINÓPOLIS", "eleitorado": 4543},
  {"municipio": "FRANCISCO AYRES", "eleitorado": 5308},
  {"municipio": "FRANCISCO MACEDO", "eleitorado": 2808},
  {"municipio": "FRANCISCO SANTOS", "eleitorado": 7156},
  {"municipio": "FRONTEIRAS", "eleitorado": 9676},
  {"municipio": "GEMINIANO", "eleitorado": 6474},
  {"municipio": "GILBUÉS", "eleitorado": 8452},
  {"municipio": "GUADALUPE", "eleitorado": 8986},
  {"municipio": "GUARIBAS", "eleitorado": 4553},
  {"municipio": "HUGO NAPOLEÃO", "eleitorado": 4499},
  {"municipio": "ILHA GRANDE", "eleitorado": 9604},
  {"municipio": "INHUMA", "eleitorado": 13254},
  {"municipio": "IPIRANGA DO PIAUÍ", "eleitorado": 7738},
  {"municipio": "ISAÍAS COELHO", "eleitorado": 6479},
  {"municipio": "ITAINÓPOLIS", "eleitorado": 9534},
  {"municipio": "ITAUEIRA", "eleitorado": 9398},
  {"municipio": "JACOBINA DO PIAUÍ", "eleitorado": 5154},
  {"municipio": "JAICÓS", "eleitorado": 13811},
  {"municipio": "JARDIM DO MULATO", "eleitorado": 4606},
  {"municipio": "JATOBÁ DO PIAUÍ", "eleitorado": 6852},
  {"municipio": "JERUMENHA", "eleitorado": 5105},
  {"municipio": "JOÃO COSTA", "eleitorado": 4052},
  {"municipio": "JOAQUIM PIRES", "eleitorado": 11995},
  {"municipio": "JOCA MARQUES", "eleitorado": 5566},
  {"municipio": "JOSÉ DE FREITAS", "eleitorado": 34708},
  {"municipio": "JUAZEIRO DO PIAUÍ", "eleitorado": 5484},
  {"municipio": "JÚLIO BORGES", "eleitorado": 5282},
  {"municipio": "JUREMA", "eleitorado": 5399},
  {"municipio": "LAGOA ALEGRE", "eleitorado": 8527},
  {"municipio": "LAGOA DE SÃO FRANCISCO", "eleitorado": 6156},
  {"municipio": "LAGOA DO BARRO DO PIAUÍ", "eleitorado": 4509},
  {"municipio": "LAGOA DO PIAUÍ", "eleitorado": 5281},
  {"municipio": "LAGOA DO SÍTIO", "eleitorado": 4843},
  {"municipio": "LAGOINHA DO PIAUÍ", "eleitorado": 3280},
  {"municipio": "LANDRI SALES", "eleitorado": 5263},
  {"municipio": "LUIS CORREIA", "eleitorado": 27118},
  {"municipio": "LUZILÂNDIA", "eleitorado": 20198},
  {"municipio": "MADEIRO", "eleitorado": 6787},
  {"municipio": "MANOEL EMÍDIO", "eleitorado": 4974},
  {"municipio": "MARCOLÂNDIA", "eleitorado": 8622},
  {"municipio": "MARCOS PARENTE", "eleitorado": 4362},
  {"municipio": "MASSAPÊ DO PIAUÍ", "eleitorado": 6552},
  {"municipio": "MATIAS OLÍMPIO", "eleitorado": 9234},
  {"municipio": "MIGUEL ALVES", "eleitorado": 27663},
  {"municipio": "MIGUEL LEÃO", "eleitorado": 1911},
  {"municipio": "MILTON BRANDÃO", "eleitorado": 7176},
  {"municipio": "MONSENHOR GIL", "eleitorado": 10371},
  {"municipio": "MONSENHOR HIPÓLITO", "eleitorado": 7438},
  {"municipio": "MONTE ALEGRE DO PIAUÍ", "eleitorado": 9667},
  {"municipio": "MORRO CABEÇA NO TEMPO", "eleitorado": 4200},
  {"municipio": "MORRO DO CHAPÉU DO PIAUÍ", "eleitorado": 5884},
  {"municipio": "MURICI DOS PORTELAS", "eleitorado": 6070},
  {"municipio": "NAZARÉ DO PIAUÍ", "eleitorado": 6927},
  {"municipio": "NAZÁRIA", "eleitorado": 11662},
  {"municipio": "NOSSA SENHORA DE NAZARÉ", "eleitorado": 5909},
  {"municipio": "NOSSA SENHORA DOS REMÉDIOS", "eleitorado": 8590},
  {"municipio": "NOVA SANTA RITA", "eleitorado": 4180},
  {"municipio": "NOVO ORIENTE DO PIAUÍ", "eleitorado": 5222},
  {"municipio": "NOVO SANTO ANTÔNIO", "eleitorado": 4843},
  {"municipio": "OEIRAS", "eleitorado": 31213},
  {"municipio": "OLHO D'ÁGUA DO PIAUÍ", "eleitorado": 2766},
  {"municipio": "PADRE MARCOS", "eleitorado": 6120},
  {"municipio": "PAES LANDIM", "eleitorado": 4638},
  {"municipio": "PAJEÚ DO PIAUÍ", "eleitorado": 3354},
  {"municipio": "PALMEIRA DO PIAUÍ", "eleitorado": 5011},
  {"municipio": "PALMEIRAIS", "eleitorado": 13507},
  {"municipio": "PAQUETÁ", "eleitorado": 4209},
  {"municipio": "PARNAGUÁ", "eleitorado": 7730},
  {"municipio": "PARNAÍBA", "eleitorado": 115019},
  {"municipio": "PASSAGEM FRANCA DO PIAUÍ", "eleitorado": 4318},
  {"municipio": "PATOS DO PIAUÍ", "eleitorado": 5508},
  {"municipio": "PAU D'ARCO DO PIAUÍ", "eleitorado": 5245},
  {"municipio": "PAULISTANA", "eleitorado": 16886},
  {"municipio": "PAVUSSU", "eleitorado": 3923},
  {"municipio": "PEDRO II", "eleitorado": 35147},
  {"municipio": "PEDRO LAURENTINO", "eleitorado": 3332},
  {"municipio": "PICOS", "eleitorado": 53325},
  {"municipio": "PIMENTEIRAS", "eleitorado": 9521},
  {"municipio": "PIO IX", "eleitorado": 14870},
  {"municipio": "PIRACURUCA", "eleitorado": 25776},
  {"municipio": "PIRIPIRI", "eleitorado": 53078},
  {"municipio": "PORTO", "eleitorado": 9784},
  {"municipio": "PORTO ALEGRE DO PIAUÍ", "eleitorado": 2170},
  {"municipio": "PRATA DO PIAUÍ", "eleitorado": 3731},
  {"municipio": "QUEIMADA NOVA", "eleitorado": 7107},
  {"municipio": "REDENÇÃO DO GURGUÉIA", "eleitorado": 7105},
  {"municipio": "REGENERAÇÃO", "eleitorado": 14770},
  {"municipio": "RIACHO FRIO", "eleitorado": 4484},
  {"municipio": "RIBEIRA DO PIAUÍ", "eleitorado": 3907},
  {"municipio": "RIBEIRO GONÇALVES", "eleitorado": 5505},
  {"municipio": "RIO GRANDE DO PIAUÍ", "eleitorado": 5432},
  {"municipio": "SANTA CRUZ DO PIAUÍ", "eleitorado": 5799},
  {"municipio": "SANTA CRUZ DOS MILAGRES", "eleitorado": 4010},
  {"municipio": "SANTA FILOMENA", "eleitorado": 5572},
  {"municipio": "SANTA LUZ", "eleitorado": 5297},
  {"municipio": "SANTANA DO PIAUÍ", "eleitorado": 4200},
  {"municipio": "SANTA ROSA DO PIAUÍ", "eleitorado": 5032},
  {"municipio": "SANTO ANTÔNIO DE LISBOA", "eleitorado": 6441},
  {"municipio": "SANTO ANTÔNIO DOS MILAGRES", "eleitorado": 1933},
  {"municipio": "SANTO INÁCIO DO PIAUÍ", "eleitorado": 3699},
  {"municipio": "SÃO BRAZ DO PIAUÍ", "eleitorado": 4175},
  {"municipio": "SÃO FÉLIX DO PIAUÍ", "eleitorado": 4007},
  {"municipio": "SÃO FRANCISCO DE ASSIS DO PIAUÍ", "eleitorado": 4695},
  {"municipio": "SÃO FRANCISCO DO PIAUÍ", "eleitorado": 6289},
  {"municipio": "SÃO GONÇALO DO GURGUÉIA", "eleitorado": 2958},
  {"municipio": "SÃO GONÇALO DO PIAUÍ", "eleitorado": 5259},
  {"municipio": "SÃO JOÃO DA CANABRAVA", "eleitorado": 4514},
  {"municipio": "SÃO JOÃO DA FRONTEIRA", "eleitorado": 5369},
  {"municipio": "SÃO JOÃO DA SERRA", "eleitorado": 6926},
  {"municipio": "SÃO JOÃO DA VARJOTA", "eleitorado": 4186},
  {"municipio": "SÃO JOÃO DO ARRAIAL", "eleitorado": 7584},
  {"municipio": "SÃO JOÃO DO PIAUÍ", "eleitorado": 14762},
  {"municipio": "SÃO JOSÉ DO DIVINO", "eleitorado": 5084},
  {"municipio": "SÃO JOSÉ DO PEIXE", "eleitorado": 3470},
  {"municipio": "SÃO JOSÉ DO PIAUÍ", "eleitorado": 6028},
  {"municipio": "SÃO JULIÃO", "eleitorado": 5493},
  {"municipio": "SÃO LOURENÇO DO PIAUÍ", "eleitorado": 4938},
  {"municipio": "SÃO LUIS DO PIAUÍ", "eleitorado": 3685},
  {"municipio": "SÃO MIGUEL DA BAIXA GRANDE", "eleitorado": 2784},
  {"municipio": "SÃO MIGUEL DO FIDALGO", "eleitorado": 2998},
  {"municipio": "SÃO MIGUEL DO TAPUIO", "eleitorado": 15965},
  {"municipio": "SÃO PEDRO DO PIAUÍ", "eleitorado": 11505},
  {"municipio": "SÃO RAIMUNDO NONATO", "eleitorado": 26680},
  {"municipio": "SEBASTIÃO BARROS", "eleitorado": 4629},
  {"municipio": "SEBASTIÃO LEAL", "eleitorado": 4115},
  {"municipio": "SIGEFREDO PACHECO", "eleitorado": 9148},
  {"municipio": "SIMÕES", "eleitorado": 12268},
  {"municipio": "SIMPLÍCIO MENDES", "eleitorado": 10279},
  {"municipio": "SOCORRO DO PIAUÍ", "eleitorado": 4412},
  {"municipio": "SUSSUAPARA", "eleitorado": 6796},
  {"municipio": "TAMBORIL DO PIAUÍ", "eleitorado": 2964},
  {"municipio": "TANQUE DO PIAUÍ", "eleitorado": 2768},
  {"municipio": "TERESINA", "eleitorado": 585832},
  {"municipio": "UNIÃO", "eleitorado": 37900},
  {"municipio": "URUÇUÍ", "eleitorado": 18697},
  {"municipio": "VALENÇA DO PIAUÍ", "eleitorado": 17376},
  {"municipio": "VÁRZEA BRANCA", "eleitorado": 4782},
  {"municipio": "VÁRZEA GRANDE", "eleitorado": 4293},
  {"municipio": "VERA MENDES", "eleitorado": 3683},
  {"municipio": "VILA NOVA DO PIAUÍ", "eleitorado": 2982},
  {"municipio": "WALL FERRAZ", "eleitorado": 4333}
]
